picsellia/__init__.py
picsellia/client.py
picsellia/colors.py
picsellia/compatibility.py
picsellia/decorators.py
picsellia/exceptions.py
picsellia/exif.py
picsellia/pxl_multithreading.py
picsellia/sdk/__init__.py
picsellia/sdk/annotation.py
picsellia/sdk/annotation_campaign.py
picsellia/sdk/annotation_campaign_step.py
picsellia/sdk/artifact.py
picsellia/sdk/asset.py
picsellia/sdk/campaign/__init__.py
picsellia/sdk/campaign/abstract_campaign.py
picsellia/sdk/campaign/abstract_step.py
picsellia/sdk/classification.py
picsellia/sdk/connexion.py
picsellia/sdk/dao.py
picsellia/sdk/data.py
picsellia/sdk/data_projection.py
picsellia/sdk/datalake.py
picsellia/sdk/dataset.py
picsellia/sdk/dataset_version.py
picsellia/sdk/datasource.py
picsellia/sdk/deployment.py
picsellia/sdk/downloadable.py
picsellia/sdk/evaluation.py
picsellia/sdk/experiment.py
picsellia/sdk/fast_training.py
picsellia/sdk/job.py
picsellia/sdk/label.py
picsellia/sdk/label_group.py
picsellia/sdk/line.py
picsellia/sdk/log.py
picsellia/sdk/logging_file.py
picsellia/sdk/model.py
picsellia/sdk/model_context.py
picsellia/sdk/model_file.py
picsellia/sdk/model_version.py
picsellia/sdk/multi_object.py
picsellia/sdk/point.py
picsellia/sdk/polygon.py
picsellia/sdk/predicted_asset.py
picsellia/sdk/processing.py
picsellia/sdk/project.py
picsellia/sdk/rectangle.py
picsellia/sdk/resource.py
picsellia/sdk/review_campaign.py
picsellia/sdk/review_campaign_step.py
picsellia/sdk/tag.py
picsellia/sdk/taggable.py
picsellia/sdk/user.py
picsellia/sdk/worker.py
picsellia/services/__init__.py
picsellia/services/asset_splitter.py
picsellia/services/campaign.py
picsellia/services/coco_file_builder.py
picsellia/services/coco_importer.py
picsellia/services/data_uploader.py
picsellia/services/datasource.py
picsellia/services/error_manager.py
picsellia/services/lister/__init__.py
picsellia/services/lister/asset_lister.py
picsellia/services/lister/data_lister.py
picsellia/services/lister/default.py
picsellia-6.28.1.dist-info/METADATA
picsellia-6.28.1.dist-info/WHEEL
picsellia-6.28.1.dist-info/licenses/LICENSE
picsellia-6.28.1.dist-info/RECORD
