Metadata-Version: 2.4
Name: picsellia
Version: 6.28.1
Summary: Python SDK package for Picsellia MLOps platform
License-Expression: MIT
License-File: LICENSE
Keywords: ai,picsellia,sdk,cvops
Author: Pierre-Nicolas Tiffreau
Author-email: <pierre-nicolas@picsellia.com>
Requires-Python: >=3.10, <3.15
Classifier: Development Status :: 5 - Production/Stable
Classifier: Topic :: Scientific/Engineering :: Artificial Intelligence
Classifier: Topic :: Software Development :: Libraries :: Python Modules
Requires-Dist: Pillow (>=9.2.0)
Requires-Dist: beartype (>=0.16.0)
Requires-Dist: deprecation (>=2.1.0,<3.0.0)
Requires-Dist: orjson (>=3.9)
Requires-Dist: picsellia-annotations (>=0.12.1,<0.13.0)
Requires-Dist: picsellia-connexion-services (>=0.3.0,<0.4.0)
Requires-Dist: pydantic (>=2,<3)
Requires-Dist: pyyaml (>=6.0.1,<7.0.0)
Requires-Dist: requests (>=2.32)
Requires-Dist: semantic-version (>=2.10.0,<3.0.0)
Requires-Dist: tqdm (>=4.66.5,<5.0.0)
